LICENSE.txt
MANIFEST.in
README.md
changelog.md
requirements.txt
setup.py
bearcart/__init__.py
bearcart/__init__.pyc
bearcart/bearcart.py
bearcart/bearcart.pyc
bearcart/rickshaw.min.css
bearcart/rickshaw.min.js
bearcart.egg-info/PKG-INFO
bearcart.egg-info/SOURCES.txt
bearcart.egg-info/dependency_links.txt
bearcart.egg-info/top_level.txt
bearcart/templates/__init__.py
bearcart/templates/__init__.pyc
bearcart/templates/bcart_template.html
bearcart/templates/chart_css.css
bearcart/templates/graph.js
bearcart/templates/hover.js
bearcart/templates/legend.js
bearcart/templates/palette.js
bearcart/templates/x_axis.js
bearcart/templates/x_axis_num.js
bearcart/templates/y_axis.js