Metadata-Version: 1.1
Name: bearcart
Version: 0.1.2
Summary: Python Pandas + Rickshaw.js = BearCart
Home-page: https://github.com/wrobstory/bearcart
Author: Rob Story
Author-email: wrobstory@gmail.com
License: MIT License
Keywords: data visualization
Platform: UNKNOWN
Classifier: Development Status :: 4 - Beta
Classifier: Programming Language :: Python :: 2.7
Classifier: License :: OSI Approved :: MIT License
